causallm/__init__.py
causallm/_version.py
causallm/cli.py
causallm/enhanced_causal_llm.py
causallm/enhanced_causallm.py
causallm/performance_demo.py
causallm/web.py
causallm/config/__init__.py
causallm/config/settings.py
causallm/core/__init__.py
causallm/core/async_processing.py
causallm/core/caching.py
causallm/core/causal_discovery.py
causallm/core/causal_llm_core.py
causallm/core/counterfactual_engine.py
causallm/core/dag_parser.py
causallm/core/data_processing.py
causallm/core/do_operator.py
causallm/core/enhanced_causal_discovery.py
causallm/core/exceptions.py
causallm/core/factory.py
causallm/core/interfaces.py
causallm/core/lazy_evaluation.py
causallm/core/llm_client.py
causallm/core/optimized_algorithms.py
causallm/core/prompt_templates.py
causallm/core/statistical_inference.py
causallm/core/statistical_methods.py
causallm/core/validation.py
causallm/core/utils/__init__.py
causallm/core/utils/data_utils.py
causallm/core/utils/logging.py
causallm/core/utils/validation.py
causallm/domains/__init__.py
causallm/domains/base/__init__.py
causallm/domains/base/analysis_templates.py
causallm/domains/base/data_generator.py
causallm/domains/base/domain_knowledge.py
causallm/domains/education/__init__.py
causallm/domains/experimentation/__init__.py
causallm/domains/healthcare/__init__.py
causallm/domains/healthcare/generators/__init__.py
causallm/domains/healthcare/generators/clinical_data.py
causallm/domains/healthcare/generators/patient_outcomes.py
causallm/domains/healthcare/knowledge/__init__.py
causallm/domains/healthcare/knowledge/medical_knowledge.py
causallm/domains/healthcare/templates/__init__.py
causallm/domains/healthcare/templates/outcomes_research.py
causallm/domains/healthcare/templates/treatment_analysis.py
causallm/domains/insurance/__init__.py
causallm/domains/insurance/generators/__init__.py
causallm/domains/insurance/generators/insurance_data.py
causallm/domains/insurance/knowledge/__init__.py
causallm-4.3.0.dist-info/licenses/LICENSE
causallm-4.3.0.dist-info/METADATA
causallm-4.3.0.dist-info/WHEEL
causallm-4.3.0.dist-info/entry_points.txt
causallm-4.3.0.dist-info/top_level.txt
causallm-4.3.0.dist-info/RECORD
