Metadata-Version: 2.4
Name: causallm
Version: 4.3.0
Summary: Production-ready causal inference with comprehensive monitoring, testing, and LLM integration
Home-page: https://github.com/rdmurugan/causallm
Author: CausalLLM Team
Author-email: CausalLLM Team <durai@infinidatum.net>
Project-URL: Homepage, https://github.com/rdmurugan/causallm
Project-URL: Bug Tracker, https://github.com/rdmurugan/causallm/issues
Project-URL: Repository, https://github.com/rdmurugan/causallm
Keywords: causal-inference,machine-learning,statistics,llm,artificial-intelligence,monitoring,testing,property-based-testing,benchmarking,mutation-testing
Classifier: Development Status :: 4 - Beta
Classifier: Intended Audience :: Developers
Classifier: Intended Audience :: Science/Research
Classifier: License :: Other/Proprietary License
Classifier: Operating System :: OS Independent
Classifier: Programming Language :: Python :: 3
Classifier: Programming Language :: Python :: 3.9
Classifier: Programming Language :: Python :: 3.10
Classifier: Programming Language :: Python :: 3.11
Classifier: Programming Language :: Python :: 3.12
Classifier: Topic :: Scientific/Engineering :: Artificial Intelligence
Classifier: Topic :: Scientific/Engineering :: Mathematics
Classifier: Topic :: Software Development :: Libraries :: Python Modules
Requires-Python: >=3.9
License-File: LICENSE
Requires-Dist: numpy>=1.21.0
Requires-Dist: pandas>=1.3.0
Requires-Dist: scikit-learn>=1.0.0
Requires-Dist: networkx>=2.6.0
Requires-Dist: scipy>=1.7.0
Requires-Dist: matplotlib>=3.3.0
Requires-Dist: plotly>=5.0.0
Requires-Dist: openai>=1.0.0
Requires-Dist: numba>=0.56.0
Requires-Dist: dask>=2022.1.0
Requires-Dist: psutil>=5.8.0
Requires-Dist: pyyaml>=6.0.0
Requires-Dist: aiofiles>=23.0.0
Requires-Dist: pyarrow>=10.0.0
Provides-Extra: dev
Requires-Dist: pytest>=7.0.0; extra == "dev"
Requires-Dist: pytest-asyncio>=0.21.0; extra == "dev"
Requires-Dist: pytest-cov>=4.0.0; extra == "dev"
Requires-Dist: black>=22.0.0; extra == "dev"
Requires-Dist: flake8>=4.0.0; extra == "dev"
Requires-Dist: mypy>=1.0.0; extra == "dev"
Requires-Dist: pre-commit>=3.0.0; extra == "dev"
Provides-Extra: testing
Requires-Dist: hypothesis>=6.0.0; extra == "testing"
Requires-Dist: pytest-benchmark>=4.0.0; extra == "testing"
Requires-Dist: mutmut>=2.0.0; extra == "testing"
Requires-Dist: pytest-xdist>=3.0.0; extra == "testing"
Requires-Dist: pytest-mock>=3.0.0; extra == "testing"
Provides-Extra: plugins
Requires-Dist: langchain>=0.0.200; extra == "plugins"
Requires-Dist: llama-index>=0.7.0; extra == "plugins"
Requires-Dist: transformers>=4.20.0; extra == "plugins"
Requires-Dist: torch>=1.11.0; extra == "plugins"
Provides-Extra: ui
Requires-Dist: streamlit>=1.25.0; extra == "ui"
Requires-Dist: dash>=2.10.0; extra == "ui"
Requires-Dist: gradio>=3.35.0; extra == "ui"
Provides-Extra: full
Requires-Dist: langchain>=0.0.200; extra == "full"
Requires-Dist: llama-index>=0.7.0; extra == "full"
Requires-Dist: transformers>=4.20.0; extra == "full"
Requires-Dist: torch>=1.11.0; extra == "full"
Requires-Dist: streamlit>=1.25.0; extra == "full"
Requires-Dist: dash>=2.10.0; extra == "full"
Requires-Dist: gradio>=3.35.0; extra == "full"
Requires-Dist: anthropic>=0.7.0; extra == "full"
Requires-Dist: hypothesis>=6.0.0; extra == "full"
Requires-Dist: pytest-benchmark>=4.0.0; extra == "full"
Requires-Dist: mutmut>=2.0.0; extra == "full"
Requires-Dist: pytest-xdist>=3.0.0; extra == "full"
Requires-Dist: pytest-mock>=3.0.0; extra == "full"
Dynamic: author
Dynamic: home-page
Dynamic: license-file
Dynamic: requires-python
